passPkg/__init__.py
passPkg/pkgPass.py
passPkg-3.1.1.dist-info/LICENSE.txt
passPkg-3.1.1.dist-info/METADATA
passPkg-3.1.1.dist-info/WHEEL
passPkg-3.1.1.dist-info/top_level.txt
passPkg-3.1.1.dist-info/RECORD
